pystrayfix/__init__.py
pystrayfix/_appindicator.py
pystrayfix/_base.py
pystrayfix/_darwin.py
pystrayfix/_dummy.py
pystrayfix/_gtk.py
pystrayfix/_info.py
pystrayfix/_win32.py
pystrayfix/_xorg.py
pystrayfix/_util/__init__.py
pystrayfix/_util/gtk.py
pystrayfix/_util/notify_dbus.py
pystrayfix/_util/win32.py
pystrayfix-0.19.6.dist-info/licenses/COPYING.LGPL
pystrayfix-0.19.6.dist-info/METADATA
pystrayfix-0.19.6.dist-info/WHEEL
pystrayfix-0.19.6.dist-info/top_level.txt
pystrayfix-0.19.6.dist-info/zip-safe
pystrayfix-0.19.6.dist-info/RECORD
