Metadata-Version: 2.4
Name: pystrayfix
Version: 0.19.6
Summary: Provides systray integration
Home-page: https://github.com/AuroraWright/pystrayfix
Author: Moses Palmér
Author-email: fallingluma@gmail.com
License: LGPLv3
Keywords: system tray icon,systray icon
Classifier: Development Status :: 4 - Beta
Classifier: Intended Audience :: Developers
Classifier: License :: OSI Approved :: GNU Lesser General Public License v3 (LGPLv3)
Classifier: Operating System :: MacOS :: MacOS X
Classifier: Operating System :: Microsoft :: Windows :: Windows NT/2000
Classifier: Operating System :: POSIX
Classifier: Programming Language :: Python
Classifier: Programming Language :: Python :: 3.4
License-File: COPYING.LGPL
Requires-Dist: Pillow
Requires-Dist: pyobjc-framework-Quartz>=7.0; sys_platform == "darwin"
Requires-Dist: python-xlib>=0.17; sys_platform == "linux"
Dynamic: author
Dynamic: author-email
Dynamic: classifier
Dynamic: home-page
Dynamic: keywords
Dynamic: license
Dynamic: license-file
Dynamic: provides-extra
Dynamic: requires-dist
Dynamic: summary
